actxa_insights/__init__.py
actxa_insights/bgm.py
actxa_insights/config.py
actxa_insights-1.0.1.dist-info/METADATA
actxa_insights-1.0.1.dist-info/WHEEL
actxa_insights-1.0.1.dist-info/top_level.txt
actxa_insights-1.0.1.dist-info/RECORD
